pyislam/__init__.py
pyislam/exceptions.py
pyislam/quran.py
pyislam-0.1.1.dist-info/LICENSE
pyislam-0.1.1.dist-info/METADATA
pyislam-0.1.1.dist-info/WHEEL
pyislam-0.1.1.dist-info/top_level.txt
pyislam-0.1.1.dist-info/RECORD
