Metadata-Version: 2.1
Name: pyislam
Version: 0.1.1
Summary: An Islamic Python Package
Home-page: https://github.com/moha369/pyislam
Author: Mohammed Shaawa
Author-email: mshaawa963@gmail.com
License: MIT
Keywords: islam quran sunnah
Platform: UNKNOWN
Classifier: Programming Language :: Python :: 3
Classifier: License :: OSI Approved :: MIT License
Classifier: Operating System :: OS Independent
Requires-Python: >=3.6
Requires-Dist: requests
